enron_reader
