Metadata-Version: 1.0
Name: enron-reader
Version: 0.25
Summary: This package makes reading emails from Enron dataset easy.
Home-page: https://github.com/zerocogtech/enron_reader
Author: Sparik Hayrapetyan
Author-email: sparikhayrapetyan@gmail.com
License: MIT
Platform: UNKNOWN
